analog_daddy/__init__.py
analog_daddy/conf.py
analog_daddy/importer.py
analog_daddy/look_up.py
analog_daddy/utils.py
analog_daddy/write_config.py
analog_daddy-2.0.1.dist-info/licenses/LICENSE
analog_daddy-2.0.1.dist-info/METADATA
analog_daddy-2.0.1.dist-info/WHEEL
analog_daddy-2.0.1.dist-info/top_level.txt
analog_daddy-2.0.1.dist-info/RECORD
