Metadata-Version: 2.4
Name: analog_daddy
Version: 2.0.1
Summary: This library is an attempt to make transistor sizing for Analog Design less painful.
Home-page: https://github.com/siddhantladdha/analog_daddy
Author: Siddhant Laddha
Author-email: 25705822+siddhantladdha@users.noreply.github.com
License: AGPLv3
License-File: LICENSE
Requires-Dist: jupyterlab==4.4.3
Requires-Dist: scipy==1.15.2
Requires-Dist: numpy==2.3.0
Requires-Dist: matplotlib==3.10.3
Requires-Dist: dash==3.0.4
Requires-Dist: pandas==2.3.0
Provides-Extra: dev
Requires-Dist: twine; extra == "dev"
Requires-Dist: build; extra == "dev"
Dynamic: license-file
